AutoDiff/AD.py
AutoDiff/__init__.py
CommandLies_autodiff-0.0.1.dist-info/LICENSE
CommandLies_autodiff-0.0.1.dist-info/METADATA
CommandLies_autodiff-0.0.1.dist-info/WHEEL
CommandLies_autodiff-0.0.1.dist-info/top_level.txt
CommandLies_autodiff-0.0.1.dist-info/RECORD
