Metadata-Version: 2.1
Name: CommandLies-autodiff
Version: 0.0.1
Summary: Testing our autodiff package
Home-page: https://github.com/cs107-CommandLies/cs107-FinalProject
Author: Elizabeth Suitor, Lauryn Wu, Emil Gilkes, Robert Roessler
Author-email: emil_ghitmangilkes@g.harvard.edu
License: UNKNOWN
Platform: UNKNOWN
Classifier: Programming Language :: Python :: 3
Classifier: License :: OSI Approved :: MIT License
Classifier: Operating System :: OS Independent
Requires-Python: >=3.6
License-File: LICENSE
Requires-Dist: numpy
Requires-Dist: pytest
